snapchat_dl/__init__.py
snapchat_dl/app.py
snapchat_dl/cli.py
snapchat_dl/downloader.py
snapchat_dl/snapchat_dl.py
snapchat_dl/utils.py
snapchat_dl/version.py
snapchat_dl-2.0.1.dist-info/AUTHORS.rst
snapchat_dl-2.0.1.dist-info/LICENSE
snapchat_dl-2.0.1.dist-info/METADATA
snapchat_dl-2.0.1.dist-info/WHEEL
snapchat_dl-2.0.1.dist-info/entry_points.txt
snapchat_dl-2.0.1.dist-info/top_level.txt
snapchat_dl-2.0.1.dist-info/RECORD
