Metadata-Version: 2.1
Name: snapchat-dl
Version: 2.0.1
Summary: Snapchat Public Stories Downloader.
Home-page: https://github.com/skyme5/snapchat-dl
Author: Aakash Gajjar
Author-email: skyqutip@gmail.com
License: MIT license
Keywords: snapchat-dl
Platform: UNKNOWN
Classifier: Development Status :: 5 - Production/Stable
Classifier: Environment :: Console
Classifier: Intended Audience :: Developers
Classifier: Intended Audience :: End Users/Desktop
Classifier: License :: OSI Approved :: MIT License
Classifier: Natural Language :: English
Classifier: Programming Language :: Python :: 3
Requires-Python: >=3.5
